imagetext_py-2.2.0.dist-info/METADATA
imagetext_py-2.2.0.dist-info/WHEEL
imagetext_py-2.2.0.dist-info/license_files/LICENSE
imagetext_py/imagetext_py.pyi
imagetext_py/lib.py
imagetext_py/py.typed
imagetext_py/__init__.py
imagetext_py/imagetext_py.pyd
imagetext_py-2.2.0.dist-info/RECORD
