Metadata-Version: 2.1
Name: imagetext_py
Version: 2.2.0
Classifier: Programming Language :: Rust
Classifier: Programming Language :: Python :: Implementation :: CPython
Classifier: Programming Language :: Python :: Implementation :: PyPy
License-File: LICENSE
Summary: Python bindings for imagetext
Author: Nathaniel Fernandes
Author-email: Nathaniel Fernandes <nathaniel.s.fernandes@gmail.com>
Requires-Python: >=3.8
Project-URL: Repository, https://github.com/nathanielfernandes/imagetext-py
